models/__init__.py
models/sine.py
models/vco.py
pythams/__init__.py
pythams/core/__init__.py
pythams/core/block.py
pythams/core/expr.py
pythams/core/fixedpoint.py
pythams/core/fpexpr.py
pythams/core/fsmblock.py
pythams/core/integer.py
pythams/core/intervals.py
pythams/core/intexpr.py
pythams/core/rtl.py
pythams/core/sysvar.py
PythAMS-0.0.5.dist-info/LICENSE
PythAMS-0.0.5.dist-info/METADATA
PythAMS-0.0.5.dist-info/WHEEL
PythAMS-0.0.5.dist-info/top_level.txt
PythAMS-0.0.5.dist-info/RECORD
